README.md
setup.py
generator/__init__.py
generator/generator.py
generator/caches/__init__.py
generator/caches/base.py
generator/caches/local.py
generator/caches/none.py
generator/caches/redis.py
generator/caches/s3.py
mee6_image_generator.egg-info/PKG-INFO
mee6_image_generator.egg-info/SOURCES.txt
mee6_image_generator.egg-info/dependency_links.txt
mee6_image_generator.egg-info/requires.txt
mee6_image_generator.egg-info/top_level.txt
mee6_image_generator.egg-info/zip-safe