Metadata-Version: 1.0
Name: mee6-image-generator
Version: 1.0.1
Summary: Image generator
Home-page: UNKNOWN
Author: Mee6 Team
Author-email: dev@mee6bot.com
License: MIT
Platform: UNKNOWN
